{
  "itemid": "minecraft:spawn_egg",
  "displayname": "§9Apprentice (NPC)",
  "nbttag": "{ExtraAttributes:{id:\"APPRENTICE_NPC\"},HideFlags:254,ItemModel:\"minecraft:villager_spawn_egg\",display:{Lore:[0:\"\"],Name:\"§9Apprentice (NPC)\"}}",
  "damage": 120,
  "lore": [
    ""
  ],
  "internalname": "APPRENTICE_NPC",
  "clickcommand": "",
  "crafttext": "",
  "modver": "Firmament 44.2.0-dev+mc1.21.11+g36d974dd",
  "infoType": "",
  "info": [],
  "island": "hub",
  "x": -153,
  "y": 63,
  "z": -34
}