{
  "internalname": "DIAMOND_LEGGINGS",
  "itemid": "minecraft:diamond_leggings",
  "displayname": "Diamond Leggings",
  "clickcommand": "",
  "damage": 0,
  "nbttag": "{Unbreakable:1b,HideFlags:254,display:{Lore:[0:\"§7Defense: §a+30\",1:\"\",2:\"§7§8This item can be reforged!\",3:\"§a§lUNCOMMON LEGGINGS\"],Name:\"§aDiamond Leggings\"},ExtraAttributes:{originTag:\"SHOP_PURCHASE\",id:\"DIAMOND_LEGGINGS\",uuid:\"70dc215e-638b-405f-9160-b3bfc9af5c92\",timestamp:\"3/30/20 6:21 AM\"}}",
  "modver": "1.0.0",
  "lore": [
    "§7Defense: §a+30",
    "",
    "§7§8This item can be reforged!",
    "§a§lUNCOMMON LEGGINGS"
  ]
}