{
  "itemid": "minecraft:iron_axe",
  "displayname": "§cScavenged Iron Hammer",
  "nbttag": "{ench:[],Unbreakable:1b,HideFlags:254,display:{Lore:[0:\"§7Strong enough to break the\",1:\"§7toughest bars.\",2:\"\",3:\"§8§l* §8Soulbound §8§l*\",4:\"§c§lSPECIAL\"],Name:\"§cScavenged Iron Hammer\"},ExtraAttributes:{id:\"DWARVEN_IRON_HAMMER\"}}",
  "damage": 0,
  "lore": [
    "§7Strong enough to break the",
    "§7toughest bars.",
    "",
    "§8§l* §8Soulbound §8§l*",
    "§c§lSPECIAL"
  ],
  "internalname": "DWARVEN_IRON_HAMMER",
  "crafttext": "",
  "clickcommand": "",
  "modver": "2.1.0-REL",
  "infoType": "WIKI_URL",
  "info": [
    "https://hypixel-skyblock.fandom.com/wiki/Scavenged_Iron_Hammer",
    "https://wiki.hypixel.net/Scavenged_Iron_Hammer"
  ]
}