{
  "internalname": "HEAVY_CHESTPLATE",
  "itemid": 299,
  "displayname": "§5Smart Heavy Chestplate",
  "clickcommand": "",
  "damage": 0,
  "nbttag": "{HideFlags:254,display:{Lore:[0:\"§7Gear Score: §d561 §8(725)\",1:\"§7Health: §a+87 HP §8(Smart +12 HP) §8(+113.1 HP)\",2:\"§7Defense: §a+209 §8(Smart +12) §8(+271.7)\",3:\"§7Speed: §a-5\",4:\"§7Intelligence: §a+80 §8(Smart +80) §8(+104)\",5:\"\",6:\"§9Growth V, §9Protection V\",7:\"§9Thorns III\",8:\"\",9:\"§6Full Set Bonus: Vindicate\",10:\"§7Grants §f+1 walk speed §7for\",11:\"§7every §a50 §7defense that you\",12:\"§7have.\",13:\"\",14:\"§aPerfect 35000 / 35000\",15:\"§5§lEPIC DUNGEON CHESTPLATE\"],color:8553090,Name:\"§5Smart Heavy Chestplate\"},ExtraAttributes:{color:\"130:130:130\",baseStatBoostPercentage:50,modifier:\"smart\",originTag:\"UNKNOWN\",id:\"HEAVY_CHESTPLATE\",enchantments:{thorns:3,protection:5,growth:5},uuid:\"4c4b0c01-6b42-4466-8e9b-d3c079eb8a7f\",item_tier:2,timestamp:\"7/7/20 10:52 PM\"}}",
  "modver": "1.0.0",
  "lore": [
    "§7Gear Score: §d561 §8(725)",
    "§7Health: §a+87 HP §8(Smart +12 HP) §8(+113.1 HP)",
    "§7Defense: §a+209 §8(Smart +12) §8(+271.7)",
    "§7Speed: §a-5",
    "§7Intelligence: §a+80 §8(Smart +80) §8(+104)",
    "",
    "§9Growth V, §9Protection V",
    "§9Thorns III",
    "",
    "§6Full Set Bonus: Vindicate",
    "§7Grants §f+1 walk speed §7for",
    "§7every §a50 §7defense that you",
    "§7have.",
    "",
    "§aPerfect 35000 / 35000",
    "§5§lEPIC DUNGEON CHESTPLATE"
  ]
}