{
  "itemid": "minecraft:wooden_pickaxe",
  "displayname": "§aJungle Pickaxe",
  "nbttag": "{ExtraAttributes:{id:\"JUNGLE_PICKAXE\"},HideFlags:254,ItemModel:\"minecraft:wooden_pickaxe\",Unbreakable:1B,display:{Lore:[0:\"§8Breaking Power 5\",1:\"\",2:\"§7Damage: §c+50\",3:\"§7Mining Speed: §a+330\",4:\"\",5:\"§7Gives a chance to drop §aSludge Juice\",6:\"§7when mining in the §2Jungle §7of the\",7:\"§5Crystal Hollows§7.\",8:\"\",9:\"§8This item can be reforged!\",10:\"§4❣ §cRequires §5Heart of the Mountain Tier 3§c.\",11:\"§a§lUNCOMMON PICKAXE\"],Name:\"§aJungle Pickaxe\"},ench:[]}",
  "damage": 0,
  "lore": [
    "§8Breaking Power 5",
    "",
    "§7Damage: §c+50",
    "§7Mining Speed: §a+330",
    "",
    "§7Gives a chance to drop §aSludge Juice",
    "§7when mining in the §2Jungle §7of the",
    "§5Crystal Hollows§7.",
    "",
    "§8This item can be reforged!",
    "§4❣ §cRequires §5Heart of the Mountain Tier 3§c.",
    "§a§lUNCOMMON PICKAXE"
  ],
  "internalname": "JUNGLE_PICKAXE",
  "clickcommand": "",
  "crafttext": "Requires: HotM 3",
  "modver": "Firmament 3.2.0-dev+mc1.21.5+g64ef955",
  "infoType": "WIKI_URL",
  "info": [
    "https://hypixel-skyblock.fandom.com/wiki/Jungle_Pickaxe",
    "https://wiki.hypixel.net/Jungle_Pickaxe"
  ]
}