{
  "itemid": "minecraft:enchanted_book",
  "displayname": "§fEnchanted Book",
  "nbttag": "{ench:[],HideFlags:254,display:{Lore:[0:\"§9Lethality IV\",1:\"§7Reduces the armor of your target\",2:\"§7by §a4.0% §7for §68 §7seconds\",3:\"§7each time you hit them with\",4:\"§7melee. Stacks up to §a5 §7times.\",5:\"\",6:\"§7Use this on an item in an Anvil\",7:\"§7to apply it!\",8:\"\",9:\"§f§lCOMMON\"],Name:\"§fEnchanted Book\"},ExtraAttributes:{id:\"ENCHANTED_BOOK\",enchantments:{lethality:4}}}",
  "damage": 0,
  "lore": [
    "§9Lethality IV",
    "§7Reduces the armor of your target",
    "§7by §a4.0% §7for §68 §7seconds",
    "§7each time you hit them with",
    "§7melee. Stacks up to §a5 §7times.",
    "",
    "§7Use this on an item in an Anvil",
    "§7to apply it!",
    "",
    "§f§lCOMMON"
  ],
  "recipe": {
    "A1": "",
    "A2": "",
    "A3": "",
    "B1": "",
    "B2": "PAPER:8",
    "B3": "PAPER:8",
    "C1": "",
    "C2": "PAPER:8",
    "C3": "OBSIDIAN:24"
  },
  "internalname": "LETHALITY",
  "clickcommand": "viewrecipe",
  "modver": "1.0.0"
}