{
  "internalname": "SKELETON_SOLDIER_BOOTS",
  "itemid": 301,
  "displayname": "§5Mythic Skeleton Soldier Boots",
  "clickcommand": "",
  "damage": 0,
  "nbttag": "{ench:[0:{lvl:3,id:8}],HideFlags:254,display:{Lore:[0:\"§7Gear Score: §d294 §8(324)\",1:\"§7Strength: §c+8 §8(Mythic +8) §8(+8.96)\",2:\"§7Crit Chance: §c+7% §8(Mythic +4%)\",3:\"§7Crit Damage: §c+23% §8(+25.76%)\",4:\"\",5:\"§7Health: §a+102 HP §8(Mythic +8 HP) §8(+114.24 HP)\",6:\"§7Defense: §a+52 §8(Mythic +8) §8(+58.24)\",7:\"§7Speed: §a+2 §8(Mythic +2) §8(+2.24)\",8:\"§7Intelligence: §a+40 §8(Mythic +40) §8(+44.8)\",9:\"\",10:\"§9Depth Strider III, §9Feather Falling V\",11:\"§9Growth V, §9Protection V\",12:\"§9Thorns III\",13:\"\",14:\"§7Increase the damage you deal\",15:\"§7with arrows by §c5%§7.\",16:\"\",17:\"§6Full Set Bonus: Skeleton Soldier\",18:\"§7Increase the damage you deal\",19:\"§7with arrows by an extra §c25%§7.\",20:\"\",21:\"§aPerfect 52500 / 52500\",22:\"§7§4❣ §cRequires §aCatacombs Level\",23:\"§a9\",24:\"§5§lEPIC DUNGEON BOOTS\"],color:16759819,Name:\"§5Mythic Skeleton Soldier Boots\"},ExtraAttributes:{color:\"255:188:11\",baseStatBoostPercentage:31,modifier:\"mythic\",id:\"SKELETON_SOLDIER_BOOTS\",enchantments:{depth_strider:3,thorns:3,feather_falling:5,protection:5,growth:5},item_tier:1}}",
  "modver": "1.0.0",
  "lore": [
    "§7Gear Score: §d294 §8(324)",
    "§7Strength: §c+8 §8(Mythic +8) §8(+8.96)",
    "§7Crit Chance: §c+7% §8(Mythic +4%)",
    "§7Crit Damage: §c+23% §8(+25.76%)",
    "",
    "§7Health: §a+102 HP §8(Mythic +8 HP) §8(+114.24 HP)",
    "§7Defense: §a+52 §8(Mythic +8) §8(+58.24)",
    "§7Speed: §a+2 §8(Mythic +2) §8(+2.24)",
    "§7Intelligence: §a+40 §8(Mythic +40) §8(+44.8)",
    "",
    "§9Depth Strider III, §9Feather Falling V",
    "§9Growth V, §9Protection V",
    "§9Thorns III",
    "",
    "§7Increase the damage you deal",
    "§7with arrows by §c5%§7.",
    "",
    "§6Full Set Bonus: Skeleton Soldier",
    "§7Increase the damage you deal",
    "§7with arrows by an extra §c25%§7.",
    "",
    "§aPerfect 52500 / 52500",
    "§7§4❣ §cRequires §aCatacombs Level",
    "§a9",
    "§5§lEPIC DUNGEON BOOTS"
  ]
}