{
  "itemid": "minecraft:glowstone_dust",
  "displayname": "§5Spell Powder",
  "nbttag": "{ench:[],HideFlags:254,display:{Lore:[0:\"§7§7§oLooks like Sulphur, smells\",1:\"§7§olike Sulphur... Suspicious.\",2:\"\",3:\"§eRight-click to view recipes!\",4:\"\",5:\"§8§l* §8Co-op Soulbound §8§l*\",6:\"§5§lEPIC\"],Name:\"§5Spell Powder\"},ExtraAttributes:{id:\"SPELL_POWDER\"}}",
  "damage": 0,
  "lore": [
    "§7§7§oLooks like Sulphur, smells",
    "§7§olike Sulphur... Suspicious.",
    "",
    "§eRight-click to view recipes!",
    "",
    "§8§l* §8Co-op Soulbound §8§l*",
    "§5§lEPIC"
  ],
  "internalname": "SPELL_POWDER",
  "crafttext": "",
  "clickcommand": "",
  "modver": "2.1.0-REL",
  "infoType": "WIKI_URL",
  "info": [
    "https://hypixel-skyblock.fandom.com/wiki/Spell_Powder",
    "https://wiki.hypixel.net/Spell_Powder"
  ]
}