{
  "itemid": "minecraft:glowstone_dust",
  "displayname": "§aSulphur",
  "nbttag": "{HideFlags:254,display:{Lore:[0:\"§7§7§o\\\"Give me some Sulphur and\",1:\"§7§oI\u0027ll make a wand. Give me all\",2:\"§7§othe Sulphur and I\u0027ll conquer the\",3:\"§7§oworld.\\\" - Unnamed Mage.\",4:\"\",5:\"§a§lUNCOMMON\"],Name:\"§aSulphur\"},ExtraAttributes:{id:\"SULPHUR_ORE\"}}",
  "damage": 0,
  "lore": [
    "§7§7§o\"Give me some Sulphur and",
    "§7§oI\u0027ll make a wand. Give me all",
    "§7§othe Sulphur and I\u0027ll conquer the",
    "§7§oworld.\" - Unnamed Mage.",
    "",
    "§a§lUNCOMMON"
  ],
  "internalname": "SULPHUR_ORE",
  "crafttext": "",
  "clickcommand": "",
  "modver": "2.1.0-REL",
  "infoType": "WIKI_URL",
  "info": [
    "https://hypixel-skyblock.fandom.com/wiki/Sulphur",
    "https://wiki.hypixel.net/Sulphur"
  ]
}