{
  "itemid": "minecraft:diamond_hoe",
  "displayname": "§5Turing Sugar Cane Hoe Mk. III",
  "nbttag": "{ExtraAttributes:{id:\"THEORETICAL_HOE_CANE_3\",levelable_exp:0.0D,levelable_lvl:1},HideFlags:254,ItemModel:\"minecraft:diamond_hoe\",Unbreakable:1B,display:{Lore:[0:\"§8Farming Tool\",1:\"\",2:\"§7Sugar Cane Fortune: §6+4\",3:\"§7Farming Wisdom: §3+1\",4:\"\",5:\"§7Level §a1 §8-> §62   §8(0/1k)\",6:\"§f§l§m                         §r §e0§6%\",7:\"\",8:\"§8This item can be reforged!\",9:\"§4❣ §cRequires §aFarming Skill 20§c.\",10:\"§4❣ §cRequires §aGarden Level 5§c.\",11:\"§5§lEPIC FARMING TOOL\"],Name:\"§5Turing Sugar Cane Hoe Mk. III\"}}",
  "damage": 0,
  "lore": [
    "§8Farming Tool",
    "",
    "§7Sugar Cane Fortune: §6+4",
    "§7Farming Wisdom: §3+1",
    "",
    "§7Level §a1 §8-> §62   §8(0/1k)",
    "§f§l§m                         §r §e0§6%",
    "",
    "§8This item can be reforged!",
    "§4❣ §cRequires §aFarming Skill 20§c.",
    "§4❣ §cRequires §aGarden Level 5§c.",
    "§5§lEPIC FARMING TOOL"
  ],
  "internalname": "THEORETICAL_HOE_CANE_3",
  "clickcommand": "viewrecipe",
  "crafttext": "",
  "modver": "Firmament 44.1.0-dev+mc1.21.11+gcd885b38",
  "infoType": "WIKI_URL",
  "info": [
    "https://hypixelskyblock.minecraft.wiki/w/Turing_Sugar_Cane_Hoe",
    "https://wiki.hypixel.net/Turing_Sugar_Cane_Hoe"
  ],
  "recipes": [
    {
      "A1": "JACOBS_TICKET:64",
      "A2": "ENCHANTED_SUGAR_CANE:40",
      "A3": "JACOBS_TICKET:64",
      "B1": "ENCHANTED_SUGAR_CANE:40",
      "B2": "THEORETICAL_HOE_CANE_2:1",
      "B3": "ENCHANTED_SUGAR_CANE:40",
      "C1": "JACOBS_TICKET:64",
      "C2": "ENCHANTED_SUGAR_CANE:40",
      "C3": "JACOBS_TICKET:64",
      "type": "crafting",
      "count": 1,
      "overrideOutputId": "THEORETICAL_HOE_CANE_3"
    }
  ]
}