{
  "itemid": "minecraft:enchanted_book",
  "displayname": "§f§f§fEnchanted Book",
  "nbttag": "{ench:[],overrideMeta:1b,HideFlags:254,display:{Lore:[0:\"§9Turbo-Potato IV\",1:\"§7Increases double-drop chance\",2:\"§7of potato by §a+20%§7.\",3:\"§7Requires §fSilver §7in §apotato §7contest!\",4:\"\",5:\"§7Use this on an item in an Anvil\",6:\"§7to apply it!\",7:\"\",8:\"§f§lCOMMON\"],Name:\"§f§f§fEnchanted Book\"},ExtraAttributes:{originTag:\"UNKNOWN\",id:\"TURBO_POTATO;4\",enchantments:{turbo_potato:4},uuid:\"5bbd17b9-7984-4b42-9022-1b8ac4b88eb5\",timestamp:\"11/13/20 8:23 PM\"},AttributeModifiers:[]}",
  "damage": 0,
  "lore": [
    "§9Turbo-Potato IV",
    "§7Increases double-drop chance",
    "§7of potato by §a+20%§7.",
    "§7Requires §fSilver §7in §apotato §7contest!",
    "",
    "§7Use this on an item in an Anvil",
    "§7to apply it!",
    "",
    "§f§lCOMMON"
  ],
  "internalname": "TURBO_POTATO;4",
  "parent": "TURBO_POTATO;1",
  "crafttext": "",
  "clickcommand": "",
  "modver": "1.5-REL",
  "infoType": ""
}