{
  "itemid": "minecraft:enchanted_book",
  "displayname": "§fEnchanted Book",
  "nbttag": "{ExtraAttributes:{enchantments:{turbo_rose:4},id:\"TURBO_ROSE;4\"},HideFlags:254,ItemModel:\"minecraft:enchanted_book\",display:{Lore:[0:\"§8Combinable in Anvil\",1:\"\",2:\"§9Turbo-Rose IV\",3:\"§7Grants §6+20☘ Wild Rose Fortune§7.\",4:\"§7Requires §cBronze §7in a §aWild Rose Contest§7!\",5:\"\",6:\"§6Source:\",7:\"§aI: §7Jacob's Farming Contest\",8:\"§aI-V: §7Bazaar\",9:\"§aVI: §6Turbo Gourd\",10:\"§aVII: §dEnchanted Turbo Gourd\",11:\"\",12:\"§6Applied To:\",13:\"§7- §fFarming Tool\",14:\"\",15:\"§f§lCOMMON\"],Name:\"§fEnchanted Book\"},ench:[]}",
  "damage": 0,
  "lore": [
    "§8Combinable in Anvil",
    "",
    "§9Turbo-Rose IV",
    "§7Grants §6+20☘ Wild Rose Fortune§7.",
    "§7Requires §cBronze §7in a §aWild Rose Contest§7!",
    "",
    "§6Source:",
    "§aI: §7Jacob's Farming Contest",
    "§aI-V: §7Bazaar",
    "§aVI: §6Turbo Gourd",
    "§aVII: §dEnchanted Turbo Gourd",
    "",
    "§6Applied To:",
    "§7- §fFarming Tool",
    "",
    "§f§lCOMMON"
  ],
  "internalname": "TURBO_ROSE;4",
  "clickcommand": "",
  "crafttext": "",
  "modver": "Firmament 3.11.0+mc1.21.7",
  "infoType": "",
  "info": [],
  "parent": "TURBO_ROSE;1"
}