{
  "itemid": "minecraft:paper",
  "displayname": "§fVisitors' Gratitude",
  "nbttag": "{ExtraAttributes:{id:\"VISITORS_GRATITUDE\"},HideFlags:254,ItemModel:\"minecraft:cake\",display:{Lore:[0:\"§7You made someone smile today! §d❤\",1:\"\",2:\"§eRight-click to view recipes!\",3:\"\",4:\"§f§lCOMMON\"],Name:\"§fVisitors' Gratitude\"}}",
  "damage": 0,
  "lore": [
    "§7You made someone smile today! §d❤",
    "",
    "§eRight-click to view recipes!",
    "",
    "§f§lCOMMON"
  ],
  "internalname": "VISITORS_GRATITUDE",
  "clickcommand": "",
  "crafttext": "",
  "modver": "Firmament 44.1.0-dev+mc1.21.11+g84c3679e",
  "infoType": "WIKI_URL",
  "info": [
    "https://hypixelskyblock.minecraft.wiki/w/Visitors%27_Gratitude"
  ]
}