{
  "internalname": "WATER_BREATHING",
  "itemid": "minecraft:potion",
  "displayname": "§fWater Breathing Potion",
  "clickcommand": "viewpotion",
  "damage": 13,
  "nbttag": "{CustomPotionEffects:[0:{Ambient:0b,Duration:20,Id:13b,Amplifier:0b}],HideFlags:254,display:{Lore:[0:\"\",1:\"§9Water Breathing\",2:\"§7Grants chance of not taking\",3:\"§7drowning damage.\",4:\"\",5:\"§f§lCOMMON\"],Name:\"§fWater Breathing Potion\"},ExtraAttributes:{id:\"WATER_BREATHING\"}}",
  "modver": "1.0.0",
  "lore": [
    "",
    "§9Water Breathing",
    "§7Grants chance of not taking",
    "§7drowning damage.",
    "",
    "§f§lCOMMON"
  ]
}