{
  "itemid": "minecraft:leather_leggings",
  "displayname": "§aWyld Leggings",
  "nbttag": "{Unbreakable:1b,HideFlags:254,display:{Lore:[0:\"§7Rift Time: §a+15s\",1:\"\",2:\"§a§lUNCOMMON LEGGINGS\"],color:3520315,Name:\"§aWyld Leggings\"},ExtraAttributes:{id:\"WYLD_LEGGINGS\"}}",
  "damage": 0,
  "lore": [
    "§7Rift Time: §a+15s",
    "",
    "§a§lUNCOMMON LEGGINGS"
  ],
  "internalname": "WYLD_LEGGINGS",
  "crafttext": "",
  "clickcommand": "",
  "modver": "2.1.1-PRE",
  "infoType": "WIKI_URL",
  "info": [
    "https://hypixel-skyblock.fandom.com/wiki/Wyld_Leggings",
    "https://wiki.hypixel.net/Wyld_Leggings"
  ]
}